yaml_lsp/__init__.py
yaml_lsp/main.py
yaml_lsp/package.json
yaml_lsp/yarn.lock
yaml_lsp/node_modules/.yarn-integrity
yaml_lsp/node_modules/.bin/esparse
yaml_lsp/node_modules/.bin/esvalidate
yaml_lsp/node_modules/.bin/installServerIntoExtension
yaml_lsp/node_modules/.bin/js-yaml
yaml_lsp/node_modules/.bin/prettier
yaml_lsp/node_modules/.bin/yaml-language-server
yaml_lsp/node_modules/agent-base/.travis.yml
yaml_lsp/node_modules/agent-base/History.md
yaml_lsp/node_modules/agent-base/README.md
yaml_lsp/node_modules/agent-base/index.d.ts
yaml_lsp/node_modules/agent-base/index.js
yaml_lsp/node_modules/agent-base/package.json
yaml_lsp/node_modules/agent-base/patch-core.js
yaml_lsp/node_modules/agent-base/test/ssl-cert-snakeoil.key
yaml_lsp/node_modules/agent-base/test/ssl-cert-snakeoil.pem
yaml_lsp/node_modules/agent-base/test/test.js
yaml_lsp/node_modules/argparse/CHANGELOG.md
yaml_lsp/node_modules/argparse/LICENSE
yaml_lsp/node_modules/argparse/README.md
yaml_lsp/node_modules/argparse/index.js
yaml_lsp/node_modules/argparse/package.json
yaml_lsp/node_modules/argparse/lib/action.js
yaml_lsp/node_modules/argparse/lib/action_container.js
yaml_lsp/node_modules/argparse/lib/argparse.js
yaml_lsp/node_modules/argparse/lib/argument_parser.js
yaml_lsp/node_modules/argparse/lib/const.js
yaml_lsp/node_modules/argparse/lib/namespace.js
yaml_lsp/node_modules/argparse/lib/utils.js
yaml_lsp/node_modules/argparse/lib/action/append.js
yaml_lsp/node_modules/argparse/lib/action/count.js
yaml_lsp/node_modules/argparse/lib/action/help.js
yaml_lsp/node_modules/argparse/lib/action/store.js
yaml_lsp/node_modules/argparse/lib/action/subparsers.js
yaml_lsp/node_modules/argparse/lib/action/version.js
yaml_lsp/node_modules/argparse/lib/action/append/constant.js
yaml_lsp/node_modules/argparse/lib/action/store/constant.js
yaml_lsp/node_modules/argparse/lib/action/store/false.js
yaml_lsp/node_modules/argparse/lib/action/store/true.js
yaml_lsp/node_modules/argparse/lib/argument/error.js
yaml_lsp-0.2.1.dist-info/LICENSE
yaml_lsp-0.2.1.dist-info/METADATA
yaml_lsp-0.2.1.dist-info/WHEEL
yaml_lsp-0.2.1.dist-info/entry_points.txt
yaml_lsp-0.2.1.dist-info/top_level.txt
yaml_lsp-0.2.1.dist-info/RECORD
